LICENSE.txt
MANIFEST.in
README.md
requirements.txt
setup.cfg
setup.py
panther_core/__init__.py
panther_core/data_model.py
panther_core/detection.py
panther_core/enriched_event.py
panther_core/exceptions.py
panther_core/filter.py
panther_core/immutable.py
panther_core/policy.py
panther_core/rule.py
panther_core/testing.py
panther_core/testing_exec_output.py
panther_core/util.py
panther_core.egg-info/PKG-INFO
panther_core.egg-info/SOURCES.txt
panther_core.egg-info/dependency_links.txt
panther_core.egg-info/requires.txt
panther_core.egg-info/top_level.txt
panther_core/exec/__init__.py
panther_core/exec/common.py
panther_core/exec/results.py
panther_core/exec/task.py
panther_core/snapshots/__init__.py
panther_core/snapshots/_func.py